invenio_record_importer_kcworks
