Metadata-Version: 2.1
Name: invenio-record-importer-kcworks
Version: 0.2.20a7
Summary: Bulk import records into a InvenioRDM instance configured for Knowledge Commons Works
Author-email: Mesh Research <scottia4@msu.edu>
License: MIT License
Project-URL: Homepage, https://github.com/Knowledge-Commons-Works/invenio-record-importer-kcworks
Keywords: invenio,invenio-rdm,knowledge-commons-works,bulk-import,record-importer
Classifier: License :: OSI Approved :: MIT License
Classifier: Programming Language :: Python
Classifier: Programming Language :: Python :: 3
Classifier: Programming Language :: Python :: 3.12
Classifier: Environment :: Web Environment
Classifier: Intended Audience :: Developers
Classifier: Operating System :: OS Independent
Classifier: Topic :: Internet :: WWW/HTTP :: Dynamic Content
Classifier: Topic :: Software Development :: Libraries :: Python Modules
Requires-Python: >=3.9
License-File: LICENSE
Requires-Dist: click
Requires-Dist: halo
Requires-Dist: invenio-app-rdm[opensearch2]<13.0.0
Requires-Dist: invenio-communities
Requires-Dist: invenio-group-collections
Requires-Dist: invenio-rdm-records
Requires-Dist: invenio-records-resources
Requires-Dist: invenio-remote-user-data-kcworks
Requires-Dist: invenio-saml
Requires-Dist: invenio-utilities-tuw
Requires-Dist: isbnlib
Requires-Dist: jsonlines
Requires-Dist: langdetect
Requires-Dist: pytest
Requires-Dist: python-dateutil
Requires-Dist: python-iso639
Requires-Dist: python-stdnum
Requires-Dist: pytz
Requires-Dist: requests
Requires-Dist: timefhuman
Requires-Dist: titlecase
Requires-Dist: unidecode
Requires-Dist: validators
Provides-Extra: dev
Requires-Dist: bumpver; extra == "dev"
Requires-Dist: check-manifest; extra == "dev"
Requires-Dist: coverage; extra == "dev"
Requires-Dist: docker-services-cli; extra == "dev"
Requires-Dist: ipykernel; extra == "dev"
Requires-Dist: pip-tools; extra == "dev"
Requires-Dist: pytest-invenio; extra == "dev"
Requires-Dist: selenium; extra == "dev"
Provides-Extra: test
Requires-Dist: coverage; extra == "test"
